vcf2clinvar-0.1.dev3.data/scripts/clinvar_report.py
vcf2clinvar/common.py
vcf2clinvar/__init__.py
vcf2clinvar/clinvar_update.py
vcf2clinvar/genome.py
vcf2clinvar/clinvar.py
vcf2clinvar-0.1.dev3.dist-info/WHEEL
vcf2clinvar-0.1.dev3.dist-info/metadata.json
vcf2clinvar-0.1.dev3.dist-info/METADATA
vcf2clinvar-0.1.dev3.dist-info/RECORD
vcf2clinvar-0.1.dev3.dist-info/DESCRIPTION.rst
vcf2clinvar-0.1.dev3.dist-info/top_level.txt
