Metadata-Version: 2.0
Name: vcf2clinvar
Version: 0.1.dev3
Summary: Match a personal genome VCF datafile to ClinVar
Home-page: https://github.com/PersonalGenomesOrg/vcf2clinvar
Author: Personal Genome Project Informatics Group
Author-email: pgp-informatics@arvados.org
License: MIT
Platform: UNKNOWN
Classifier: Development Status :: 1 - Planning
